spatiopath/__init__.py
spatiopath/engine.py
spatiopath/helpers.py
spatiopath-0.1.0.dist-info/METADATA
spatiopath-0.1.0.dist-info/WHEEL
spatiopath-0.1.0.dist-info/licenses/LICENSE
spatiopath-0.1.0.dist-info/RECORD
