Metadata-Version: 2.4
Name: spatiopath
Version: 0.1.0
Summary: A toolkit for spatial pathology analysis
Author-email: Mounib <mbenimam@pasteur.fr>
License: GPL-3.0
License-File: LICENSE
Requires-Python: >=3.9
Requires-Dist: matplotlib
Requires-Dist: numpy
Requires-Dist: opencv-python
Requires-Dist: pandas
Requires-Dist: scikit-image
Requires-Dist: scipy
Requires-Dist: seaborn
Requires-Dist: shapely
Requires-Dist: tqdm
